examples/__init__.py
examples/utils/__init__.py
examples/utils/prepare_env.py
examples/ws/__init__.py
examples/ws/advanced_websocket_example.py
examples/ws/websocket_example.py
qe/__init__.py
qe/__version__.py
qe/api.py
qe/error.py
qe/lib/__init__.py
qe/lib/authentication.py
qe/lib/enums.py
qe/lib/trading_enums.py
qe/lib/utils.py
qe/pub/__init__.py
qe/pub/trading.py
qe/status/__init__.py
qe/status/ping.py
qe/status/timestamp.py
qe/user/__init__.py
qe/user/exchange.py
qe/user/trading.py
qe/ws/__init__.py
qe/ws/client.py
qe/ws/types.py
qe_connector-1.0.23.dist-info/licenses/LICENSE
qe_connector-1.0.23.dist-info/METADATA
qe_connector-1.0.23.dist-info/WHEEL
qe_connector-1.0.23.dist-info/top_level.txt
qe_connector-1.0.23.dist-info/RECORD
