Metadata-Version: 2.4
Name: qe-connector
Version: 1.0.23
Summary: This is a lightweight library that works as a connector to Quantum Execute public API.
Home-page: https://github.com/Quantum-Execute/qe-connector-python
Author: Quantum-Execute
License: MIT
Keywords: Quantum-Execute,Public API
Classifier: Intended Audience :: Developers
Classifier: Intended Audience :: Financial and Insurance Industry
Classifier: License :: OSI Approved :: MIT License
Classifier: Programming Language :: Python :: 3.8
Classifier: Programming Language :: Python :: 3.9
Classifier: Programming Language :: Python :: 3.10
Classifier: Programming Language :: Python :: 3.11
Requires-Python: >=3.8
License-File: LICENSE
Requires-Dist: requests>=2.31.0
Requires-Dist: websocket-client>=1.6.3
Requires-Dist: websockets>=11.0.3
Requires-Dist: pycryptodome>=3.15.0
Dynamic: author
Dynamic: classifier
Dynamic: description
Dynamic: description-content-type
Dynamic: home-page
Dynamic: keywords
Dynamic: license
Dynamic: license-file
Dynamic: requires-dist
Dynamic: requires-python
Dynamic: summary
